culqi/__init__.py
culqi/client.py
culqi/version.py
culqi/resources/__init__.py
culqi/resources/base.py
culqi/resources/card.py
culqi/resources/charge.py
culqi/resources/customer.py
culqi/resources/event.py
culqi/resources/iin.py
culqi/resources/order.py
culqi/resources/plan.py
culqi/resources/refund.py
culqi/resources/subscription.py
culqi/resources/token.py
culqi/resources/transfer.py
culqi/utils/__init__.py
culqi/utils/encoder.py
culqi/utils/errors.py
culqi/utils/status_codes.py
culqi/utils/urls.py
culqi_python_oficial-2.0.5.dist-info/LICENSE.txt
culqi_python_oficial-2.0.5.dist-info/METADATA
culqi_python_oficial-2.0.5.dist-info/WHEEL
culqi_python_oficial-2.0.5.dist-info/top_level.txt
culqi_python_oficial-2.0.5.dist-info/RECORD
