Metadata-Version: 2.1
Name: culqi-python-oficial
Version: 2.0.5
Summary: Biblioteca de Culqi en Python
Home-page: https://github.com/culqi/culqi
Download-URL: https://github.com/culqi/culqi/-/archive/2.0.5/culqi-python-oficial-2.0.5.tar.gz
Author: Willy Aguirre, Joel Ibaceta, Martin Josemaría
Keywords: Api Client,Payment Integration,Culqi,Python 3,Python 2
Classifier: Development Status :: 5 - Production/Stable
Classifier: Intended Audience :: Developers
Classifier: License :: OSI Approved :: MIT License
Classifier: Natural Language :: English
Classifier: Programming Language :: Python :: 2.7
Classifier: Programming Language :: Python :: 3.5
Classifier: Programming Language :: Python :: 3.6
Classifier: Programming Language :: Python :: 3.7
Classifier: Programming Language :: Python :: 3.8
Classifier: Topic :: Software Development :: Libraries :: Python Modules
Requires: requests
Requires: jsonschema
License-File: LICENSE.txt
Requires-Dist: requests
Requires-Dist: jsonschema
